aidev_agent-1.0.8.post1.dist-info/METADATA
aidev_agent-1.0.8.post1.dist-info/WHEEL
aidev_agent-1.0.8.post1.dist-info/entry_points.txt
aidev_agent-1.0.8.post1.dist-info/licenses/LICENSE.txt
aidev_agent/__init__.py
aidev_agent/api/__init__.py
aidev_agent/api/abstract_client.py
aidev_agent/api/base.py
aidev_agent/api/bk_aidev.py
aidev_agent/api/bkaidev_client/__init__.py
aidev_agent/api/bkaidev_client/client.py
aidev_agent/api/constants.py
aidev_agent/api/domains.py
aidev_agent/api/ssm_client.py
aidev_agent/api/utils.py
aidev_agent/config.py
aidev_agent/core/__init__.py
aidev_agent/core/agent/__init__.py
aidev_agent/core/agent/agents.py
aidev_agent/core/agent/hunyuan/__init__.py
aidev_agent/core/agent/hunyuan/agent.py
aidev_agent/core/agent/hunyuan/prompts.py
aidev_agent/core/agent/multimodal.py
aidev_agent/core/agent/patches.py
aidev_agent/core/agent/planner.py
aidev_agent/core/agent/prompts.py
aidev_agent/core/extend/__init__.py
aidev_agent/core/extend/agent/__init__.py
aidev_agent/core/extend/agent/qa.py
aidev_agent/core/extend/gateway/__init__.py
aidev_agent/core/extend/gateway/common.py
aidev_agent/core/extend/intent/__init__.py
aidev_agent/core/extend/intent/intent_recognition.py
aidev_agent/core/extend/intent/prompts.py
aidev_agent/core/extend/intent/similarity_model.py
aidev_agent/core/extend/intent/utils.py
aidev_agent/core/extend/models/__init__.py
aidev_agent/core/extend/models/llm_gateway.py
aidev_agent/core/utils/__init__.py
aidev_agent/core/utils/async_utils.py
aidev_agent/core/utils/common.py
aidev_agent/core/utils/langchain.py
aidev_agent/core/utils/local.py
aidev_agent/core/utils/loop.py
aidev_agent/core/utils/model_management/__init__.py
aidev_agent/core/utils/model_management/registry.py
aidev_agent/core/utils/model_management/service.py
aidev_agent/core/utils/model_management/utils.py
aidev_agent/enums.py
aidev_agent/exceptions.py
aidev_agent/packages/__init__.py
aidev_agent/packages/langchain/__init__.py
aidev_agent/packages/langchain/exceptions.py
aidev_agent/packages/langchain/tools/__init__.py
aidev_agent/packages/langchain/tools/base.py
aidev_agent/packages/langchain/tools/builtin.py
aidev_agent/packages/langchain/tools/enums.py
aidev_agent-1.0.8.post1.dist-info/RECORD
