Metadata-Version: 2.1
Name: aidev-agent
Version: 1.0.8.post1
Summary: bkaidev agent builder
Author: blueking
License: MIT
Requires-Python: <4.0,>=3.10.5
Requires-Dist: environs<15.0.0,>=14.1.0
Requires-Dist: langchain<1.0.0,>=0.3.14
Requires-Dist: langchain-openai<1.0.0,>=0.3.0
Requires-Dist: langchain-community==0.3.28
Requires-Dist: pyro4<5.0,>=4.82
Requires-Dist: langfuse<3
Requires-Dist: bkapi-client-core<2.0.0,>=1.2.0
Requires-Dist: jinja2<4.0.0,>=3.1.6
Requires-Dist: cachetools<6.0.0,>=5.5.2
Requires-Dist: asgiref<4.0.0,>=3.8.1
Requires-Dist: werkzeug<4.0.0,>=3.1.3
Requires-Dist: pytz<2026.0,>=2025.2
Requires-Dist: h11==0.16.0
Requires-Dist: langchain-mcp-adapters<1.0.0,>=0.1.9
Requires-Dist: langchain-core>0.3.79
Requires-Dist: mcp==1.25.0
Requires-Dist: urllib3>=2.6.0
